Code/Verilog/multiplier_env_1_2.v

`timescale 1ns/1ps  
module multiplier (
input [1:0] A,
input [1:0] B,
output [3:0] P);

        // Generación de productos parciales
 wire pp0 = ((~A[1]) & (~B[0]));
 wire pp1 = ((A[0]) & (B[1]));
 wire pp2 = ((~A[1]) & (B[1]));

    // Suma de productos parciales
wire [1:0] columna4 = pp1;
wire [1:0] columna2 = pp2;
wire [1:0] columna1 = pp0;
assign P = (columna4 << 3) + (columna2 << 1) + (columna1 << 0);
endmodule

Code/Verilog/multiplier_8bit_tb_env_1_2.v

`timescale 1ns/1ps
module tb_multiplier_8bit();
    // Señales de entrada
    reg [1:0] A;
    reg [1:0] B;
    
    // Señales de salida
    wire [3:0] P;

    // Instancia del módulo multiplicador
    multiplier uut (
        .A(A),
        .B(B),
        .P(P)
    );

    // Bloque inicial para pruebas
    initial begin
        
        // Caso 0: Prueba aleatoria 0
                A = 8'd3;  // Acceso más eficiente con NumPy
                B = 8'd3;
                #10;
                $display("%d", P);
                //$display("A:%b,B:%b,res:%b",A,B P);

// Caso 1: Prueba aleatoria 1
                A = 8'd1;  // Acceso más eficiente con NumPy
                B = 8'd2;
                #10;
                $display("%d", P);
                //$display("A:%b,B:%b,res:%b",A,B P);

// Caso 2: Prueba aleatoria 2
                A = 8'd1;  // Acceso más eficiente con NumPy
                B = 8'd3;
                #10;
                $display("%d", P);
                //$display("A:%b,B:%b,res:%b",A,B P);

// Caso 3: Prueba aleatoria 3
                A = 8'd1;  // Acceso más eficiente con NumPy
                B = 8'd1;
                #10;
                $display("%d", P);
                //$display("A:%b,B:%b,res:%b",A,B P);

// Caso 4: Prueba aleatoria 4
                A = 8'd2;  // Acceso más eficiente con NumPy
                B = 8'd3;
                #10;
                $display("%d", P);
                //$display("A:%b,B:%b,res:%b",A,B P);

// Caso 5: Prueba aleatoria 5
                A = 8'd3;  // Acceso más eficiente con NumPy
                B = 8'd1;
                #10;
                $display("%d", P);
                //$display("A:%b,B:%b,res:%b",A,B P);

// Caso 6: Prueba aleatoria 6
                A = 8'd3;  // Acceso más eficiente con NumPy
                B = 8'd3;
                #10;
                $display("%d", P);
                //$display("A:%b,B:%b,res:%b",A,B P);

// Caso 7: Prueba aleatoria 7
                A = 8'd2;  // Acceso más eficiente con NumPy
                B = 8'd3;
                #10;
                $display("%d", P);
                //$display("A:%b,B:%b,res:%b",A,B P);

// Caso 8: Prueba aleatoria 8
                A = 8'd1;  // Acceso más eficiente con NumPy
                B = 8'd2;
                #10;
                $display("%d", P);
                //$display("A:%b,B:%b,res:%b",A,B P);

// Caso 9: Prueba aleatoria 9
                A = 8'd2;  // Acceso más eficiente con NumPy
                B = 8'd2;
                #10;
                $display("%d", P);
                //$display("A:%b,B:%b,res:%b",A,B P);

// Caso 10: Prueba aleatoria 10
                A = 8'd2;  // Acceso más eficiente con NumPy
                B = 8'd2;
                #10;
                $display("%d", P);
                //$display("A:%b,B:%b,res:%b",A,B P);

// Caso 11: Prueba aleatoria 11
                A = 8'd2;  // Acceso más eficiente con NumPy
                B = 8'd1;
                #10;
                $display("%d", P);
                //$display("A:%b,B:%b,res:%b",A,B P);

// Caso 12: Prueba aleatoria 12
                A = 8'd2;  // Acceso más eficiente con NumPy
                B = 8'd1;
                #10;
                $display("%d", P);
                //$display("A:%b,B:%b,res:%b",A,B P);

// Caso 13: Prueba aleatoria 13
                A = 8'd2;  // Acceso más eficiente con NumPy
                B = 8'd2;
                #10;
                $display("%d", P);
                //$display("A:%b,B:%b,res:%b",A,B P);

// Caso 14: Prueba aleatoria 14
                A = 8'd2;  // Acceso más eficiente con NumPy
                B = 8'd1;
                #10;
                $display("%d", P);
                //$display("A:%b,B:%b,res:%b",A,B P);

// Caso 15: Prueba aleatoria 15
                A = 8'd1;  // Acceso más eficiente con NumPy
                B = 8'd1;
                #10;
                $display("%d", P);
                //$display("A:%b,B:%b,res:%b",A,B P);

// Caso 16: Prueba aleatoria 16
                A = 8'd1;  // Acceso más eficiente con NumPy
                B = 8'd1;
                #10;
                $display("%d", P);
                //$display("A:%b,B:%b,res:%b",A,B P);

// Caso 17: Prueba aleatoria 17
                A = 8'd3;  // Acceso más eficiente con NumPy
                B = 8'd1;
                #10;
                $display("%d", P);
                //$display("A:%b,B:%b,res:%b",A,B P);

// Caso 18: Prueba aleatoria 18
                A = 8'd1;  // Acceso más eficiente con NumPy
                B = 8'd3;
                #10;
                $display("%d", P);
                //$display("A:%b,B:%b,res:%b",A,B P);

// Caso 19: Prueba aleatoria 19
                A = 8'd3;  // Acceso más eficiente con NumPy
                B = 8'd3;
                #10;
                $display("%d", P);
                //$display("A:%b,B:%b,res:%b",A,B P);

        // Terminar simulación
        $finish;
    end

    // Generación de forma de onda (opcional)
    initial begin
        $dumpfile("multiplier_8bit_tb.vcd");
        $dumpvars(0, tb_multiplier_8bit);
    end
endmodule

Code/multiplier_8bit_tb.vcd
$date
	Tue Sep  2 19:22:12 2025
$end
$version
	Icarus Verilog
$end
$timescale
	1ps
$end
$scope module tb_multiplier_8bit $end
$var wire 4 ! P [3:0] $end
$var reg 2 " A [1:0] $end
$var reg 2 # B [1:0] $end
$scope module uut $end
$var wire 2 $ A [1:0] $end
$var wire 2 % B [1:0] $end
$var wire 1 & pp0 $end
$var wire 1 ' pp1 $end
$var wire 1 ( pp2 $end
$var wire 2 ) columna4 [1:0] $end
$var wire 2 * columna2 [1:0] $end
$var wire 2 + columna1 [1:0] $end
$var wire 4 , P [3:0] $end
$upscope $end
$upscope $end
$enddefinitions $end
$comment Show the parameter values. $end
$dumpall
$end
#0
$dumpvars
b1000 ,
b0 +
b0 *
b1 )
0(
1'
0&
b11 %
b11 $
b11 #
b11 "
b1000 !
$end
#10000
b1011 !
b1011 ,
b1 +
1&
b1 *
1(
b10 #
b10 %
b1 "
b1 $
#20000
b1010 !
b1010 ,
b0 +
0&
b11 #
b11 %
#30000
b0 !
b0 ,
b0 )
0'
b0 *
0(
b1 #
b1 %
#40000
b11 #
b11 %
b10 "
b10 $
#50000
b1 #
b1 %
b11 "
b11 $
#60000
b1000 !
b1000 ,
b1 )
1'
b11 #
b11 %
#70000
b0 !
b0 ,
b0 )
0'
b10 "
b10 $
#80000
b1 +
1&
b1011 !
b1011 ,
b1 *
1(
b1 )
1'
b10 #
b10 %
b1 "
b1 $
#90000
b0 +
0&
b0 !
b0 ,
b0 *
0(
b0 )
0'
b10 "
b10 $
#110000
b1 #
b1 %
#130000
b10 #
b10 %
#140000
b1 #
b1 %
#150000
b1 "
b1 $
#170000
b11 "
b11 $
#180000
b1010 !
b1010 ,
b1 )
1'
b1 *
1(
b11 #
b11 %
b1 "
b1 $
#190000
b1000 !
b1000 ,
b0 *
0(
b11 "
b11 $
